llama_index/llms/keywordsai/__init__.py
llama_index/llms/keywordsai/base.py
llama_index/llms/keywordsai/utils.py
llama_index_llms_keywordsai-1.1.2.dist-info/METADATA
llama_index_llms_keywordsai-1.1.2.dist-info/WHEEL
llama_index_llms_keywordsai-1.1.2.dist-info/licenses/LICENSE
llama_index_llms_keywordsai-1.1.2.dist-info/RECORD
